mongo_export_index_clean-1.0.0.dist-info/DESCRIPTION.rst
mongo_export_index_clean-1.0.0.dist-info/METADATA
mongo_export_index_clean-1.0.0.dist-info/RECORD
mongo_export_index_clean-1.0.0.dist-info/WHEEL
mongo_export_index_clean-1.0.0.dist-info/entry_points.txt
mongo_export_index_clean-1.0.0.dist-info/metadata.json
mongo_export_index_clean-1.0.0.dist-info/top_level.txt
mongoexportindexclean/__init__.py
