Metadata-Version: 2.0
Name: mongo-export-index-clean
Version: 1.0.0
Summary: Utility to clean records from a mongodb bson export file with too large fields for indexes.
Home-page: https://github.com/sverrirab/mongo-export-index-clean
Author: Sverrir Á. Berg <sab@keilir.com>
Author-email: UNKNOWN
License: Apache
Keywords: mongo,mongodb,bson,index
Platform: UNKNOWN
Classifier: Development Status :: 5 - Production/Stable
Classifier: License :: OSI Approved :: Apache Software License
Classifier: Intended Audience :: Information Technology
Classifier: Operating System :: OS Independent
Classifier: Programming Language :: Python
Classifier: Programming Language :: Python :: 2
Classifier: Programming Language :: Python :: 2.7
Classifier: Programming Language :: Python :: 3
Classifier: Programming Language :: Python :: 3.5
Classifier: Topic :: Software Development :: Libraries :: Python Modules
Requires-Dist: pymongo (==3.5.1)
Requires-Dist: future (==0.16.0)
